Workbook

Sheet Inputs
A1: Patel Creative Studio — Child Employment Payroll Schedule (Tax Year 2026)
A2: Planning estimate — not a filed tax result. See 'Sources & Assumptions'.
A4: Item | B4: Value | C4: Unit | D4: Source
A5: Child age | B5: 15 | C5: years | D5: client_facts.md
A6: Documented hours (2026) | B6: 160 | C6: hours | D6: client_facts.md / calculation_inputs.csv
A7: Comparable hourly rate 1 | B7: 16 | C7: $/hour | D7: calculation_inputs.csv
A8: Comparable hourly rate 2 | B8: 18 | C8: $/hour | D8: calculation_inputs.csv
A9: Comparable hourly rate 3 | B9: 20 | C9: $/hour | D9: calculation_inputs.csv
A10: Owner proposed budget | B10: 8000 | C10: $ | D10: client_facts.md
A11: 2026 dependent std deduction floor | B11: 1350 | C11: $ | D11: official_guidance.md / IRB 2025-45
A12: 2026 dependent earned-income addition | B12: 450 | C12: $ | D12: official_guidance.md / IRB 2025-45
A13: 2026 dependent std deduction cap | B13: 16100 | C13: $ | D13: official_guidance.md / IRB 2025-45
A14: 2026 IRA/Roth contribution limit (under 50) | B14: 7500 | C14: $ | D14: IRS IR-2025-111 / Notice 2025-67
A15: 2026 Roth single full-contribution MAGI cap | B15: 153000 | C15: $ | D15: IRS IR-2025-111
A16: Social Security rate (employer) | B16: 0.062 | C16: rate | D16: IRS Pub. 15 (reference)
... A20: FUTA rate (reference) | B20: 0.006 | C20: rate | D20: IRS Pub. 15 (reference)

Sheet Wage Calculation
A1: Reasonable Wage Determination
A3: Component | B3: Value | C3: Note
A4: Comparable rate 1 | B4: =Inputs!B7 | C4: $/hour
A5: Comparable rate 2 | B5: =Inputs!B8 | C5: $/hour
A6: Comparable rate 3 | B6: =Inputs!B9 | C6: $/hour
A7: Median comparable rate | B7: =MEDIAN(B4:B6) | C7: $/hour — per client_facts.md, use median
A8: Documented hours | B8: =Inputs!B6 | C8: hours
A9: Reasonable total wages (2026) | B9: =B7*B8 | C9: median rate x documented hours
A10: Owner proposed budget | B10: =Inputs!B10 | C10: $
A11: Implied rate at owner budget | B11: =IF(B10=0,0,B10/B8) | C11: $/hour — for comparison only
A12: Budget vs. reasonable wages | B12: =B10-B9 | C12: excess of budget over reasonable pay

Sheet Payroll Taxes
A1: Federal Payroll Tax Classification — Child under 18, Sole Proprietorship
A3: Tax | B3: Statutory rate | C3: Applies? | D3: Amount (if applied) | E3: Basis
A4: Social Security (employer) | B4: =Inputs!B16 | C4: No — exempt | D4: ='Wage Calculation'!B9*Inputs!B16*0 | E4: Child under 18 in parent's sole prop.
A5: Social Security (employee) | B5: =Inputs!B17 | C5: No — exempt | D5: ='Wage Calculation'!B9*Inputs!B17*0 | E5: Child under 18 in parent's sole prop.
A6: Medicare (employer) | B6: =Inputs!B18 | C6: No — exempt | D6: ='Wage Calculation'!B9*Inputs!B18*0 | E6: Child under 18 in parent's sole prop.
A7: Medicare (employee) | B7: =Inputs!B19 | C7: No — exempt | D7: ='Wage Calculation'!B9*Inputs!B19*0 | E7: Child under 18 in parent's sole prop.
A8: FUTA (federal unemployment) | B8: =Inputs!B20 | C8: No — exempt | D8: ='Wage Calculation'!B9*Inputs!B20*0 | E8: Child under 21
A9: Federal income tax withholding | B9: n/a | C9: Yes — applies | D9: ='Wage Calculation'!B9*0 | E9: Likely $0 withheld if W-4 exempt; reporting still required
A10: Total federal payroll tax remitted | D10: =SUM(D4:D9) | E10: All exempt; FIT withholding expected $0 if W-4 exempt

Sheet Income Tax & Roth
A1: Arjun — 2026 Federal Income Tax Position & Roth IRA Capacity
A3: Component | B3: Value | C3: Note / Formula
A4: Wage income (earned income) | B4: ='Wage Calculation'!B9 | C4: Reasonable total wages from Wage Calculation
A5: Other income | B5: 0 | C5: client_facts.md: no other income
A6: AGI | B6: =B4+B5 | C6: Wages + other income
A7: Dependent std deduction floor | B7: =Inputs!B11 | C7: $1,350
A8: Earned income + addition | B8: =B4+Inputs!B12 | C8: earned income + $450
A9: Greater of floor or (EI + addition) | B9: =MAX(B7,B8) | C9: step 1 of dependent std deduction
A10: Standard deduction cap | B10: =Inputs!B13 | C10: $16,100
A11: Standard deduction (lesser of above & cap) | B11: =MIN(B9,B10) | C11: 2026 dependent standard deduction
A12: Taxable income | B12: =MAX(B6-B11,0) | C12: AGI - std deduction, not below 0
A13: Federal income tax (2026) | B13: =B12*0 | C13: Estimate: $0 — taxable income is $0; confirm brackets
A15: Roth IRA — earned income | B15: =B4 | C15: Wages
A16: Roth IRA — 2026 statutory limit | B16: =Inputs!B14 | C16: $7,500 (under 50)
A17: Roth IRA — MAGI (single) | B17: =B6 | C17: Equals wages; no other income
A18: Roth IRA — single full-contribution cap | B18: =Inputs!B15 | C18: $153,000
A19: Roth IRA — phase-out applies? | B19: =IF(B17<B18,"No","Yes") | C19: MAGI below threshold
A20: Roth IRA contribution capacity | B20: =IF(B19="No",MIN(B15,B16),0) | C20: lesser of earned income or limit

Sheet Payroll Schedule
A1: 2026 Period-by-Period Payroll Schedule (illustrative — actual dates/hours per timesheets)
A3: Period | B3: Pay date | C3: Hours | D3: Hourly rate | E3: Gross wages | F3: FICA (exempt) | G3: FIT withheld | H3: Net pay
A4: Q1 2026 | B4: 2026-03-31 | C4: 40 | D4: ='Wage Calculation'!B7 | E4: =C4*D4 | F4: 0 | G4: 0 | H4: =E4-F4-G4
A5: Q2 2026 | B5: 2026-06-30 | C5: 40 | D5: ='Wage Calculation'!B7 | E5: =C5*D5 | F5: 0 | G5: 0 | H5: =E5-F5-G5
A6: Q3 2026 | B6: 2026-09-30 | C6: 40 | D6: ='Wage Calculation'!B7 | E6: =C6*D6 | F6: 0 | G6: 0 | H6: =E6-F6-G6
A7: Q4 2026 | B7: 2026-12-31 | C7: 40 | D7: ='Wage Calculation'!B7 | E7: =C7*D7 | F7: 0 | G7: 0 | H7: =E7-F7-G7
A8: Total 2026 | C8: =SUM(C4:C7) | E8: =SUM(E4:E7) | F8: =SUM(F4:F7) | G8: =SUM(G4:G7) | H8: =SUM(H4:H7)
A10: Illustrative quarterly split of 160 hours. Actual pay dates and hours must follow contemporaneous timesheets.

Sheet Sources & Assumptions
A1: Sources & Assumptions
A3: Type | B3: Detail | C3: Source
A4: Source doc | B4: Synthetic client facts (entity, child age, hours, comparables, budget, dependent status) | C4: source_docs/client_facts.md
A5: Source doc | B5: Calculation inputs (hours, rates, std deduction parameters, budget) | C5: source_docs/calculation_inputs.csv
A6: Source doc | B6: Official guidance: family-employee FICA/FUTA exemptions, Pub. 15, 2026 dependent std deduction | C6: source_docs/official_guidance.md
A7: Federal rule | B7: Child under 18 in parent's sole proprietorship: FICA exempt; under 21: FUTA exempt; FIT withholding/reporting still applies | C7: IRS Family Employees — https://www.irs.gov/businesses/small-businesses-self-employed/family-employees
A8: Federal rule | B8: Payroll procedures, withholding forms, deposit rules, Form W-2 | C8: IRS Publication 15 — https://www.irs.gov/publications/p15
A9: Federal rule | B9: 2026 dependent standard deduction = greater of $1,350 or earned income + $450, capped at $16,100 | C9: IRS IRB 2025-45 — https://www.irs.gov/irb/2025-45_IRB
A10: Federal rule | B10: 2026 IRA/Roth contribution limit $7,500 (under 50); single full Roth MAGI cap $153,000 | C10: IRS IR-2025-111 / Notice 2025-67
A11: Assumption | B11: Median comparable ($18) used as reasonable rate per client_facts.md direction | C11: client_facts.md
A12: Assumption | B12: 160 documented hours are real, age-appropriate business work (not personal/household labor) | C12: client_facts.md
A13: Assumption | B13: Arjun claims exempt on Form W-4 (no 2025 liability, expects none for 2026) => $0 FIT withheld | C13: Derived from facts; confirm with adviser
A14: Assumption | B14: Illustrative payroll schedule splits 160 hours evenly across 4 quarters; actual dates/hours per timesheets | C14: Modeling assumption
... A22: Disclaimer | B22: All figures are planning estimates, not filed tax results. Filed amounts reflect actual paid hours and confirmed rules. | C22: —
