Workbook

Sheet Event Log
A1: Willow Strategy Inc. - Section 280A(g) Home-Rental Event & Documentation Log (Tax Year 2026)
A2: Owner: Taylor (residence, Chicago West Loop) | Renter: Willow Strategy Inc. (S corp) | Arrangement: written rental agreement, per-event invoice, corporate-account payment. No overnight lodging, personal entertainment, or mixed personal events.
A4: Event # | B4: Date | C4: Day of Week | D4: Start | E4: End | F4: Duration (hours, formula) | G4: Meeting Type | H4: Documented Business Agenda / Purpose | I4: Attendee Count | J4: Day Rate (USD, benchmark) | K4: Per-Event Payment (formula) | L4: Invoice # | M4: Payment Status | N4: Documentation Status | O4: Cumulative Rental Days (formula)
A5: 1 | B5: 46037 | C5: =TEXT(B5,"dddd") | D5: 0.375 | E5: 0.70833333 | F5: =MOD(E5-D5,1)*24 | G5: Leadership | H5: Q1 leadership offsite: 2026 strategic priorities & OKR cascade | I5: 8 | J5: ='Sources & Assumptions'!B5 | K5: =J5 | L5: WSI-2026-01 | M5: Pending | N5: Pending - collect agenda + sign-in | O5: =COUNTA($A$5:A5)
A6: 2 | B6: 46065 | C6: =TEXT(B6,"dddd") | D6: 0.375 | E6: 0.70833333 | F6: =MOD(E6-D6,1)*24 | G6: Client-planning | H6: Annual planning with Anchor Client A: roadmap & SOW scope | I6: 8 | J6: ='Sources & Assumptions'!B5 | K6: =J6 | L6: WSI-2026-02 | M6: Pending | N6: Pending - collect agenda + sign-in | O6: =O5+1
A7: 3 | B7: 46093 | C7: =TEXT(B7,"dddd") | D7: 0.375 | E7: 0.70833333 | F7: =MOD(E7-D7,1)*24 | G7: Leadership | H7: Q1 closeout & Q2 operating plan review | I7: 8 | J7: ='Sources & Assumptions'!B5 | K7: =J7 | L7: WSI-2026-03 | M7: Pending | N7: Pending - collect agenda + sign-in | O7: =O6+1
A8: 4 | B8: 46107 | C8: =TEXT(B8,"dddd") | D8: 0.375 | E8: 0.70833333 | F8: =MOD(E8-D8,1)*24 | G8: Client-planning | H8: Discovery workshop with Prospect B: solution design | I8: 8 | J8: ='Sources & Assumptions'!B5 | K8: =J8 | L8: WSI-2026-04 | M8: Pending | N8: Pending - collect agenda + sign-in | O8: =O7+1
A9: 5 | B9: 46128 | C9: =TEXT(B9,"dddd") | D9: 0.375 | E9: 0.70833333 | F9: =MOD(E9-D9,1)*24 | G9: Leadership | H9: Board prep & capital allocation working session | I9: 8 | J9: ='Sources & Assumptions'!B5 | K9: =J9 | L9: WSI-2026-05 | M9: Pending | N9: Pending - collect agenda + sign-in | O9: =O8+1
A10: 6 | B10: 46156 | C10: =TEXT(B10,"dddd") | D10: 0.375 | E10: 0.70833333 | F10: =MOD(E10-D10,1)*24 | G10: Client-planning | H10: Quarterly business review with Anchor Client C | I10: 8 | J10: ='Sources & Assumptions'!B5 | K10: =J10 | L10: WSI-2026-06 | M10: Pending | N10: Pending - collect agenda + sign-in | O10: =O9+1
A11: 7 | B11: 46184 | C11: =TEXT(B11,"dddd") | D11: 0.375 | E11: 0.70833333 | F11: =MOD(E11-D11,1)*24 | G11: Leadership | H11: Mid-year talent & compensation committee | I11: 8 | J11: ='Sources & Assumptions'!B5 | K11: =J11 | L11: WSI-2026-07 | M11: Pending | N11: Pending - collect agenda + sign-in | O11: =O10+1
A12: 8 | B12: 46212 | C12: =TEXT(B12,"dddd") | D12: 0.375 | E12: 0.70833333 | F12: =MOD(E12-D12,1)*24 | G12: Client-planning | H12: Implementation kickoff with Client D | I12: 8 | J12: ='Sources & Assumptions'!B5 | K12: =J12 | L12: WSI-2026-08 | M12: Pending | N12: Pending - collect agenda + sign-in | O12: =O11+1
A13: 9 | B13: 46247 | C13: =TEXT(B13,"dddd") | D13: 0.375 | E13: 0.70833333 | F13: =MOD(E13-D13,1)*24 | G13: Leadership | H13: Q3 strategy reset & risk register review | I13: 8 | J13: ='Sources & Assumptions'!B5 | K13: =J13 | L13: WSI-2026-09 | M13: Pending | N13: Pending - collect agenda + sign-in | O13: =O12+1
A14: 10 | B14: 46275 | C14: =TEXT(B14,"dddd") | D14: 0.375 | E14: 0.70833333 | F14: =MOD(E14-D14,1)*24 | G14: Client-planning | H14: Proposal design session with Prospect E | I14: 8 | J14: ='Sources & Assumptions'!B5 | K14: =J14 | L14: WSI-2026-10 | M14: Pending | N14: Pending - collect agenda + sign-in | O14: =O13+1
A15: 11 | B15: 46289 | C15: =TEXT(B15,"dddd") | D15: 0.375 | E15: 0.70833333 | F15: =MOD(E15-D15,1)*24 | G15: Leadership | H15: FY27 planning retreat part 1: market thesis | I15: 8 | J15: ='Sources & Assumptions'!B5 | K15: =J15 | L15: WSI-2026-11 | M15: Pending | N15: Pending - collect agenda + sign-in | O15: =O14+1
A16: 12 | B16: 46303 | C16: =TEXT(B16,"dddd") | D16: 0.375 | E16: 0.70833333 | F16: =MOD(E16-D16,1)*24 | G16: Client-planning | H16: Renewal & expansion negotiation with Anchor Client A | I16: 8 | J16: ='Sources & Assumptions'!B5 | K16: =J16 | L16: WSI-2026-12 | M16: Pending | N16: Pending - collect agenda + sign-in | O16: =O15+1
A17: 13 | B17: 46338 | C17: =TEXT(B17,"dddd") | D17: 0.375 | E17: 0.70833333 | F17: =MOD(E17-D17,1)*24 | G17: Leadership | H17: FY27 planning retreat part 2: operating budget | I17: 8 | J17: ='Sources & Assumptions'!B5 | K17: =J17 | L17: WSI-2026-13 | M17: Pending | N17: Pending - collect agenda + sign-in | O17: =O16+1
A18: 14 | B18: 46366 | C18: =TEXT(B18,"dddd") | D18: 0.375 | E18: 0.70833333 | F18: =MOD(E18-D18,1)*24 | G18: Client-planning | H18: Year-end account review & 2027 roadmap with Client C | I18: 8 | J18: ='Sources & Assumptions'!B5 | K18: =J18 | L18: WSI-2026-14 | M18: Pending | N18: Pending - collect agenda + sign-in | O18: =O17+1
A19: TOTAL | F19: =SUM(F5:F18) | I19: =SUM(I5:I18) | K19: =SUM(K5:K18) | O19: =O18
A21: 280A(g) day-count guard | B21: =IF(O18<15,"PASS - fewer than 15 rental days; 280A(g) exclusion applies to owner","FAIL - 15+ rental days; exclusion LOST for entire year")
A22: Annual payment @ benchmark (14 day rates) | B22: =K19
A23: Proposed $1,800/day annual (NOT adopted) | B23: =1800*COUNTA(A5:A18)

Sheet Sources & Assumptions
A1: Sources & Assumptions - Willow Strategy Inc. Section 280A(g) Arrangement
A3: FROZEN PLANNING BENCHMARK
A5: Median normalized 8-hour day rate (USD) | B5: 385 | C5: Median of 5 comparable asking rates in calculation_inputs.csv (288,363,385,553,754).
A6: Annual payment @ benchmark (14 days) | B6: =B5*14 | C6: Formula: benchmark x planned days
A7: Proposed $1,800/day annual (NOT adopted) | B7: =1800*14 | C7: Shown for reasonableness comparison only
A8: Proposed-to-benchmark ratio | B8: =1800/B5 | C8: 4.68x - exceeds reasonableness support
A9: Excess over benchmark (annual) | B9: =(1800-B5)*14 | C9: Amount at risk of disallowance under IRC 162
A11: Comparable | B11: Normalized day rate | C11: Notes
A12: CHI-01 Large Focus Room, Michigan Ave (cap 8) | B12: 288 | C12: $40/hr x 8hr x 90% discount
A13: CHI-02 VC Studio, Regus West Loop (cap 6) | B13: 363 | C13: Direct day rate; smaller capacity (6)
A14: CHI-03 Small Boardroom, Regus 125 S Wacker (cap 8) | B14: 385 | C14: Direct day rate - MEDIAN (benchmark)
A15: CHI-04 MR-15B, Spaces 1 N State St (cap 8) | B15: 553 | C15: Direct day rate
A16: CHI-05 MR03, Signature 110 N Wacker (cap 8) | B16: 754 | C16: Direct day rate
A17: Median (formula) | B17: =MEDIAN(B12:B16) | C17: Ties to B5 benchmark
A19: OFFICIAL AUTHORITY (2026 federal; refresh before filing)
A20: IRC 280A(g) - dwelling used as residence rented <15 days | B20: Exclusion + no rental deductions | C20: https://uscode.house.gov/view.xhtml?req=granuleid:USC-prelim-title26-section280A
A21: IRS Publication 527 | B21: Describes <15-day rule & reporting | C21: https://www.irs.gov/publications/p527
A22: IRC 162 - company deduction (separate question) | B22: Ordinary, necessary; related-party reasonableness | C22: https://uscode.house.gov/view.xhtml?req=granuleid:USC-prelim-title26-section162
A24: KEY ASSUMPTIONS
A25: Taxpayer and residence are synthetic; no real address used.
A26: Residence is not otherwise rented during 2026 (client representation; verify before filing).
A27: Exactly 14 rental days planned; a 15th day (even partial) collapses the 280A(g) exclusion for the entire year.
A28: Each meeting is 9:00-17:00, 8 attendees, documented business agenda; no overnight/personal/mixed use.
A29: Comparables are dated ASKING rates, not completed arm's-length transactions.
A30: Median is a frozen PLANNING benchmark, not a filed tax result; refresh quotes near implementation.
A31: State/local lodging or sales taxes are outside this evaluation.
A32: Written rental agreement, disinterested corporate action, per-event invoice, corporate-account payment required.
A34: EVIDENCE GAPS / CONFIRMATIONS REQUIRED
A35: Refresh comparable quotes before implementation (rates and availability change).
A36: Comparability adjustments: capacity (CHI-02 seats 6 vs 8), amenities, taxes, booking fees, cancellation terms.
... A41: Strict day-count control: monitor cumulative rental days so the 14-day limit is not breached.
